setup.py
tran/__init__.py
tran/tran.py
tran.egg-info/PKG-INFO
tran.egg-info/SOURCES.txt
tran.egg-info/dependency_links.txt
tran.egg-info/entry_points.txt
tran.egg-info/top_level.txt