Metadata-Version: 1.0
Name: tran
Version: 1.0
Summary: 方便在终端中译英和英译中的小工具
Home-page: https://github.com/kakitgogogo/Translator
Author: kakit
Author-email: kakitgo@gmail.com
License: UNKNOWN
Keywords: python terminal
Platform: UNKNOWN
